{
  "timestamp": 1774373251.3714623,
  "total_pages_analyzed": 1,
  "results": [
    {
      "url": "https://parentdataforce.com",
      "timestamp": 1774373250.4842067,
      "redirects": [],
      "final_url": "https://parentdataforce.com/",
      "status_code": 200,
      "has_public_in_path": false,
      "analysis": {
        "domain_changed": false,
        "path_changed": true,
        "has_public_in_path": false,
        "path_components": [
          ""
        ],
        "is_redirected": true,
        "possible_configurations": []
      },
      "url_analysis": {
        "scheme": "https",
        "netloc": "parentdataforce.com",
        "path": "/",
        "params": "",
        "query": "",
        "fragment": "",
        "public_position": -1
      },
      "links": [
        {
          "href": "https://fonts.googleapis.com",
          "full_url": "https://fonts.googleapis.com",
          "has_public": false
        },
        {
          "href": "https://fonts.gstatic.com",
          "full_url": "https://fonts.gstatic.com",
          "has_public": false
        },
        {
          "href": "https://fonts.googleapis.com/css2?family=Inter:wght@300;400;500;600;700;800&family=JetBrains+Mono:wght@400;500&display=swap",
          "full_url": "https://fonts.googleapis.com/css2?family=Inter:wght@300;400;500;600;700;800&family=JetBrains+Mono:wght@400;500&display=swap",
          "has_public": false
        }
      ]
    }
  ],
  "summary": {
    "total_urls_with_public": 0,
    "urls_with_public": [],
    "total_redirects": 0,
    "common_configurations": [],
    "sample_urls_analyzed": [
      "https://parentdataforce.com"
    ]
  }
}